agentvox/__init__.py
agentvox/cli.py
agentvox/record_speaker_wav.py
agentvox/voice_assistant.py
agentvox-0.2.0.dist-info/licenses/LICENSE
agentvox-0.2.0.dist-info/METADATA
agentvox-0.2.0.dist-info/WHEEL
agentvox-0.2.0.dist-info/entry_points.txt
agentvox-0.2.0.dist-info/top_level.txt
agentvox-0.2.0.dist-info/RECORD
