Metadata-Version: 2.4
Name: agentvox
Version: 0.2.0
Summary: Edge-based voice assistant using Gemma LLM with STT and TTS capabilities
Home-page: https://github.com/yourusername/agentvox
Author: MIMIC Lab
Author-email: 
License: MIT
Project-URL: Homepage, https://github.com/yourusername/agentvox
Classifier: Development Status :: 3 - Alpha
Classifier: Intended Audience :: Developers
Classifier: Programming Language :: Python :: 3
Classifier: Programming Language :: Python :: 3.8
Classifier: Programming Language :: Python :: 3.9
Classifier: Programming Language :: Python :: 3.10
Classifier: Programming Language :: Python :: 3.11
Requires-Python: >=3.8
License-File: LICENSE
Requires-Dist: torch>=2.6.0
Requires-Dist: numpy
Requires-Dist: realtimestt
Requires-Dist: realtimetts[coqui]
Requires-Dist: llama-cpp-python
Requires-Dist: pygame
Requires-Dist: sounddevice
Requires-Dist: soundfile
Requires-Dist: gradio
Requires-Dist: flask
Requires-Dist: pyaudio
Requires-Dist: hangul-romanize
Requires-Dist: mecab-python3
Requires-Dist: unidic-lite
Dynamic: home-page
Dynamic: license-file
Dynamic: requires-python
